tornado_widgets/__init__.py
tornado_widgets/app.py
tornado_widgets/error.py
tornado_widgets/handler.py
tornado_widgets/log.py
tornado_widgets/router.py
tornado_widgets/schema.py
tornado_widgets/sentry.py
tornado_widgets/utils.py
tornado_widgets/mysql/__init__.py
tornado_widgets/postgres/__init__.py
tornado_widgets/redis/__init__.py
tornado_widgets-0.0.40.dist-info/METADATA
tornado_widgets-0.0.40.dist-info/WHEEL
tornado_widgets-0.0.40.dist-info/top_level.txt
tornado_widgets-0.0.40.dist-info/RECORD
